flask_noai/__init__.py
flask_noai/py.typed
flask_noai-1.1.0.dist-info/licenses/LICENSE
flask_noai-1.1.0.dist-info/METADATA
flask_noai-1.1.0.dist-info/WHEEL
flask_noai-1.1.0.dist-info/top_level.txt
flask_noai-1.1.0.dist-info/zip-safe
flask_noai-1.1.0.dist-info/RECORD
