Metadata-Version: 2.4
Name: flask_noai
Version: 1.1.0
Summary: A simple Flask extension to block AI crawlers.
Home-page: https://ari.lt/gh/flask-noai
Author: Ari Archer
Author-email: ari@ari.lt
License: GPLv3+
Keywords: flask,ai,crawlers,llm
Classifier: Development Status :: 5 - Production/Stable
Classifier: Environment :: Web Environment
Classifier: Intended Audience :: Developers
Classifier: License :: OSI Approved :: GNU General Public License v3 or later (GPLv3+)
Classifier: Operating System :: OS Independent
Classifier: Programming Language :: Python :: 3
Classifier: Programming Language :: Python :: 3.9
Classifier: Programming Language :: Python :: 3.10
Classifier: Programming Language :: Python :: 3.11
Classifier: Programming Language :: Python :: 3.12
Classifier: Programming Language :: Python :: 3.13
Classifier: Topic :: Internet :: WWW/HTTP
Classifier: Topic :: Software Development :: Libraries :: Python Modules
Classifier: Typing :: Typed
License-File: LICENSE
Requires-Dist: flask
Dynamic: license-file
